{
    "type": "origins:active_self",
    "entity_action": {
        "type": "origins:and",
        "actions": [
            {
                "type": "origins:set_on_fire",
                "duration": 20
            },
            {
                "type": "origins:exhaust",
                "amount": 0.4
            }
        ]
    },
    "cooldown": 800,
    "hud_render": {
        "should_render": true,
        "bar_index": 7
    },
    "key": {
        "key": "key.origins.primary_active"
    },
    "name": "Inner Flame",
    "description": "You can set yourself on fire for 20 seconds every 40 seconds."
}